Metadata-Version: 2.1
Name: py4self
Version: 1.0.1
Summary: public ai using python
Home-page: UNKNOWN
Author: yourmom
Author-email: <nuga@pornhub.com>
License: UNKNOWN
Keywords: bitches
Platform: UNKNOWN
Classifier: Intended Audience :: Developers
Classifier: Programming Language :: Python :: 3
Classifier: License :: OSI Approved :: MIT License
Classifier: Operating System :: OS Independent
